readgrid/__init__.py
readgrid/pipeline.py
readgrid-0.2.6.dist-info/licenses/LICENSE
readgrid-0.2.6.dist-info/METADATA
readgrid-0.2.6.dist-info/WHEEL
readgrid-0.2.6.dist-info/top_level.txt
readgrid-0.2.6.dist-info/RECORD
