Metadata-Version: 2.4
Name: readgrid
Version: 0.2.6
Summary: A document layout pipeline for detecting tables, images, and structured extraction.
Home-page: https://github.com/davidkjeremiah/readgrid
Author: David Jeremiah
Author-email: flasconnect@gmail.com
License: MIT
Classifier: Programming Language :: Python :: 3
Classifier: License :: OSI Approved :: MIT License
Classifier: Operating System :: OS Independent
Requires-Python: >=3.8
License-File: LICENSE
Requires-Dist: opencv-python
Requires-Dist: numpy
Requires-Dist: Pillow
Requires-Dist: google-genai
Requires-Dist: ipywidgets
Requires-Dist: IPython
Dynamic: author
Dynamic: author-email
Dynamic: classifier
Dynamic: description
Dynamic: description-content-type
Dynamic: home-page
Dynamic: license
Dynamic: license-file
Dynamic: requires-dist
Dynamic: requires-python
Dynamic: summary
